emedit/__init__.py
emedit/behaviour/__init__.py
emedit/behaviour/pipeline_components/__init__.py
emedit/behaviour/pipeline_components/a01_gather/__init__.py
emedit/behaviour/pipeline_components/a02_split/__init__.py
emedit/behaviour/pipeline_components/a03_process/__init__.py
emedit/behaviour/pipeline_components/a03_process/edit/__init__.py
emedit/behaviour/pipeline_components/a03_process/search/__init__.py
emedit/behaviour/pipeline_components/a04_combine/__init__.py
emedit/behaviour/pipeline_components/a05_save/__init__.py
emedit/behaviour/pipelines/__init__.py
emedit/cli/__init__.py
emedit/structures/__init__.py
emedit/structures/embedding.py
emedit/structures/text_file.py
emedit-0.1.4.dist-info/WHEEL
emedit-0.1.4.dist-info/entry_points.txt
emedit-0.1.4.dist-info/METADATA
emedit-0.1.4.dist-info/RECORD
