Metadata-Version: 2.1
Name: emedit
Version: 0.1.4
Summary: 
License: MIT
Author: IsaacBreen
Author-email: mail@isaacbreen.com
Requires-Python: >=3.11,<4.0
Classifier: License :: OSI Approved :: MIT License
Classifier: Programming Language :: Python :: 3
Classifier: Programming Language :: Python :: 3.11
Requires-Dist: delegatefn (>=0.3.4,<0.4.0)
Requires-Dist: openai (>=0.25.0,<0.26.0)
Requires-Dist: rich (>=13.0.0,<14.0.0)
